foldersync/__init__.py
foldersync/cli.py
foldersync/core.py
foldersync-0.1.0.dist-info/LICENSE
foldersync-0.1.0.dist-info/METADATA
foldersync-0.1.0.dist-info/WHEEL
foldersync-0.1.0.dist-info/entry_points.txt
foldersync-0.1.0.dist-info/top_level.txt
foldersync-0.1.0.dist-info/RECORD
