Metadata-Version: 2.1
Name: foldersync
Version: 0.1.0
Summary: A minimalistic file and folder synchronisation utility.
Author-email: Prasant Sudhakaran <code@prasant.net>
License: MIT License
Project-URL: Homepage, https://github.com/yourusername/foldersync
Classifier: Development Status :: 3 - Alpha
Classifier: Intended Audience :: Developers
Classifier: License :: OSI Approved :: MIT License
Classifier: Programming Language :: Python :: 3
Requires-Python: >=3.7
License-File: LICENSE
